odoo/addons/contact_referred/README.rst
odoo/addons/contact_referred/__init__.py
odoo/addons/contact_referred/__manifest__.py
odoo/addons/contact_referred/i18n/es.po
odoo/addons/contact_referred/models/__init__.py
odoo/addons/contact_referred/models/res_partner.py
odoo/addons/contact_referred/static/description/icon.png
odoo/addons/contact_referred/views/res_partner_views.xml
odoo_addon_contact_referred-15.0.1.0.0.4.dist-info/METADATA
odoo_addon_contact_referred-15.0.1.0.0.4.dist-info/WHEEL
odoo_addon_contact_referred-15.0.1.0.0.4.dist-info/top_level.txt
odoo_addon_contact_referred-15.0.1.0.0.4.dist-info/RECORD
