Metadata-Version: 2.1
Name: odoo-addon-contact_referred
Version: 15.0.1.0.0.4
Summary: Referred Contact Field.
Home-page: https://github.com/sygel-technology/sy-partner-contact
Author: Sygel
License: LGPL-3
Classifier: Programming Language :: Python
Classifier: Framework :: Odoo
Classifier: Framework :: Odoo :: 15.0
Classifier: License :: OSI Approved :: GNU Lesser General Public License v3 (LGPLv3)
Requires-Python: >=3.8
Requires-Dist: odoo<15.1dev,>=15.0a
